AEML/__init__.py
AEML/data/__init__.py
AEML/data/loader.py
AEML/models/__init__.py
AEML/models/MIXER/MLP_MIXER.py
AEML/models/MIXER/__init__.py
AEML/models/MIXER/helper.py
AEML/models/MLP/__init__.py
AEML/models/MLP/class_wrapper.py
AEML/models/MLP/evaluate.py
AEML/models/MLP/flag_reader.py
AEML/models/MLP/model_maker.py
AEML/models/MLP/parameters.py
AEML/models/MLP/train.py
AEML/models/MLP/utils/__init__.py
AEML/models/MLP/utils/data_reader.py
AEML/models/MLP/utils/evaluation_helper.py
AEML/models/MLP/utils/get_mse_list.py
AEML/models/MLP/utils/get_outcome_stats.py
AEML/models/MLP/utils/helper_functions.py
AEML/models/MLP/utils/plot_swipe.py
AEML/models/MLP/utils/plotsAnalysis.py
AEML/models/MLP/utils/time_recorder.py
AEML/models/MLP/utils/total_training_time.py
AEML/models/Transformer/__init__.py
AEML/models/Transformer/class_wrapper.py
AEML/models/Transformer/model_maker.py
AEML/models/Transformer/utils/__init__.py
AEML/models/Transformer/utils/data_reader.py
AEML/models/Transformer/utils/evaluation_helper.py
AEML/models/Transformer/utils/get_mse_list.py
AEML/models/Transformer/utils/get_outcome_stats.py
AEML/models/Transformer/utils/helper_functions.py
AEML/models/Transformer/utils/plot_swipe.py
AEML/models/Transformer/utils/plotsAnalysis.py
AEML/models/Transformer/utils/time_recorder.py
AEML/models/Transformer/utils/total_training_time.py
AEML-0.0.1.dist-info/METADATA
AEML-0.0.1.dist-info/WHEEL
AEML-0.0.1.dist-info/top_level.txt
AEML-0.0.1.dist-info/RECORD
