Metadata-Version: 2.1
Name: AEML
Version: 0.0.1
Summary: Package for benchmarking deep learning models on AEM problems
Home-page: https://github.com/ydeng-MLM/ML_MM_Benchmark
Author: Yang Deng, Juncheng Dong, Simiao Ren
Author-email: yang.deng@duke.edu
License: UNKNOWN
Platform: UNKNOWN
Classifier: Programming Language :: Python :: 3
Classifier: License :: OSI Approved :: MIT License
Classifier: Operating System :: OS Independent
Requires-Python: >=3.6
